hotreload/__init__.py
hotreload/reloader.py
hotreload-2020.6.12.15.23.48.dist-info/LICENSE
hotreload-2020.6.12.15.23.48.dist-info/METADATA
hotreload-2020.6.12.15.23.48.dist-info/WHEEL
hotreload-2020.6.12.15.23.48.dist-info/top_level.txt
hotreload-2020.6.12.15.23.48.dist-info/RECORD
