Metadata-Version: 2.1
Name: hotreload
Version: 2020.6.12.15.23.48
Summary: Run any arbitrary python script every time the code changes in the file.
Home-page: https://github.com/say4n/hotreload.py
Author: Sayan Goswami
Author-email: me@sayan.page
License: UNKNOWN
Platform: UNKNOWN
Classifier: Programming Language :: Python :: 3
Classifier: License :: OSI Approved :: MIT License
Classifier: Operating System :: OS Independent
Requires-Python: >=3.6
